odoo/addons/mgmtsystem_review_survey/README.rst
odoo/addons/mgmtsystem_review_survey/__init__.py
odoo/addons/mgmtsystem_review_survey/__manifest__.py
odoo/addons/mgmtsystem_review_survey/i18n/it.po
odoo/addons/mgmtsystem_review_survey/i18n/mgmtsystem_review_survey.pot
odoo/addons/mgmtsystem_review_survey/models/__init__.py
odoo/addons/mgmtsystem_review_survey/models/mgmtsystem_review.py
odoo/addons/mgmtsystem_review_survey/readme/CONTRIBUTORS.md
odoo/addons/mgmtsystem_review_survey/readme/DESCRIPTION.md
odoo/addons/mgmtsystem_review_survey/report/review.xml
odoo/addons/mgmtsystem_review_survey/static/description/icon.png
odoo/addons/mgmtsystem_review_survey/static/description/index.html
odoo/addons/mgmtsystem_review_survey/views/mgmtsystem_review_views.xml
odoo_addon_mgmtsystem_review_survey-18.0.2.0.0.2.dist-info/METADATA
odoo_addon_mgmtsystem_review_survey-18.0.2.0.0.2.dist-info/WHEEL
odoo_addon_mgmtsystem_review_survey-18.0.2.0.0.2.dist-info/top_level.txt
odoo_addon_mgmtsystem_review_survey-18.0.2.0.0.2.dist-info/RECORD
